{
  "props": [
    {
      "name": "accept",
      "type": "string",
      "description": "Specifies the native file input `accept` attribute to describe the allow-list of file types.",
      "required": false
    },
    {
      "name": "ariaRequired",
      "type": "boolean",
      "description": "Specifies whether to add aria-required to the file upload control.",
      "required": false
    },
    {
      "name": "fileErrors",
      "type": "ReadonlyArray<null | string>",
      "description": "An array of file errors corresponding to the files in the `value`.",
      "required": false
    },
    {
      "name": "fileTokenAlignment",
      "type": "FileUploadProps.FileTokenAlignment",
      "description": "Alignment of the file tokens. Defaults to \"vertical\".",
      "required": false,
      "defaultValue": "'vertical'"
    },
    {
      "name": "fileWarnings",
      "type": "ReadonlyArray<null | string>",
      "description": "An array of file warnings corresponding to the files in the `value`.",
      "required": false
    },
    {
      "name": "i18nStrings",
      "type": "FileUploadProps.I18nStrings",
      "description": "An object containing all the localized strings required by the component:\n* `uploadButtonText` (function): A function to render the text of the file upload button. It takes `multiple` attribute to define plurality.\n* `dropzoneText` (function): A function to render the text shown in the dropzone. It takes `multiple` attribute to define plurality.\n* `removeFileAriaLabel` (function): A function to render the ARIA label for file token remove button.\n* `limitShowFewer` (string): The text of the show more tokens button.\n* `limitShowMore` (string): The text of the show fewer tokens button.\n* `errorIconAriaLabel` (string): The ARIA label to be shown on the error file icon.\n* `warningIconAriaLabel` (string): The ARIA label to be shown on the warning file icon.\n* `formatFileSize` (function): (Optional) A function that takes file size in bytes, and produces a formatted string.\n* `formatFileLastModified` (function): (Optional) A function that takes the files last modified date, and produces a formatted string.",
      "required": false
    },
    {
      "name": "multiple",
      "type": "boolean",
      "description": "Specifies the native file input `multiple` attribute to allow users entering more than one file.",
      "required": false,
      "defaultValue": "false"
    },
    {
      "name": "showFileLastModified",
      "type": "boolean",
      "description": "Show file last modified timestamp in the token. Use `i18nStrings.formatFileLastModified` to customize it.",
      "required": false,
      "defaultValue": "false"
    },
    {
      "name": "showFileSize",
      "type": "boolean",
      "description": "Show file size in the token. Use `i18nStrings.formatFileSize` to customize it.",
      "required": false,
      "defaultValue": "false"
    },
    {
      "name": "showFileThumbnail",
      "type": "boolean",
      "description": "Show file thumbnail in the token. Only supported for images.",
      "required": false,
      "defaultValue": "false"
    },
    {
      "name": "tokenLimit",
      "type": "number",
      "description": "Specifies the maximum number of displayed file tokens. If the property isn't set, all of the tokens are displayed.",
      "required": false
    },
    {
      "name": "value",
      "type": "readonly File[]",
      "description": "Specifies the currently selected file(s).\nIf you want to clear the selection, use empty array.",
      "required": true,
      "defaultValue": "[]"
    }
  ],
  "slots": [
    {
      "name": "constraintText",
      "description": "Constraint text that is displayed below the control"
    },
    {
      "name": "errorText",
      "description": "Text that displays as a validation error message"
    },
    {
      "name": "warningText",
      "description": "Text that displays as a validation warning message"
    }
  ],
  "events": [
    {
      "name": "change",
      "description": "",
      "detailType": "CustomEvent<FileUploadProps.ChangeDetail>"
    }
  ]
}
